rdadata/__init__.py
rdadata/approxequal.py
rdadata/constants.py
rdadata/energy.py
rdadata/geoutils.py
rdadata/graph.py
rdadata/misc.py
rdadata/population.py
rdadata/readwrite.py
rdadata/requireargs.py
rdadata/timers.py
rdadata/union_find.py
rdadata-1.2.3.dist-info/LICENSE
rdadata-1.2.3.dist-info/METADATA
rdadata-1.2.3.dist-info/WHEEL
rdadata-1.2.3.dist-info/top_level.txt
rdadata-1.2.3.dist-info/RECORD
