Metadata-Version: 2.1
Name: rdadata
Version: 1.2.3
Summary: Redistricting analytics data
Home-page: https://github.com/dra2020/rdadata
Author: alecramsay
Author-email: Alec Ramsay <a73cram5ay@gmail.com>
License: MIT
Project-URL: Homepage, https://github.com/dra2020/rdadata
Project-URL: Bug Tracker, https://github.com/dra2020/rdadata/issues
Classifier: Programming Language :: Python :: 3
Classifier: License :: OSI Approved :: MIT License
Classifier: Operating System :: OS Independent
Requires-Python: >=3.10
License-File: LICENSE
Requires-Dist: fiona
Requires-Dist: geopandas
Requires-Dist: libpysal
Requires-Dist: pytest
Requires-Dist: shapely
